{
  "impressum.html": {
    "date": "2022-10-01T02:52:47.607369",
    "headers": {
      "Accept-Ranges": "bytes",
      "Connection": "keep-alive",
      "Content-Length": "176014",
      "Content-Type": "text/html",
      "Date": "Sat, 01 Oct 2022 02:52:49 GMT",
      "ETag": "\"ba498eede5865e927577b25f86419d55\"",
      "Last-Modified": "Thu, 29 Sep 2022 13:26:05 GMT",
      "Server": "AmazonS3",
      "Via": "1.1 b26814b9dbe71dc1916d211eeeec7ffc.cloudfront.net (CloudFront)",
      "X-Amz-Cf-Id": "SxKyfP8Eub-go8oIBmaUOC5PyVvN4tWa70lJVHxJKL0vpfpMfECPcg==",
      "X-Amz-Cf-Pop": "IAD66-C1",
      "X-Cache": "RefreshHit from cloudfront",
      "x-amz-version-id": "yIPl9YhEuGgl1vLQxF.s.KwDU_KlBCDR"
    },
    "status": 200,
    "url": "https://www.sueddeutsche.de/datenschutz"
  },
  "index.html": {
    "date": "2022-10-01T02:52:43.897726",
    "headers": {
      "Accept-Ranges": "bytes",
      "Age": "1",
      "Cache-Control": "public,max-age=30",
      "Connection": "keep-alive",
      "Content-Security-Policy": "upgrade-insecure-requests",
      "Content-Type": "text/html; charset=UTF-8",
      "Date": "Sat, 01 Oct 2022 02:52:44 GMT",
      "Strict-Transport-Security": "max-age=31536000",
      "Transfer-Encoding": "chunked",
      "Vary": "Origin,Accept-Encoding",
      "Via": "1.1 varnish (Varnish/7.0), 1.1 a27022837959b6f70545c8d6d0de9d04.cloudfront.net (CloudFront)",
      "X-Amz-Cf-Id": "YPpb5TpKg8wDBTXWnyutB_BFoq81MeW0da1RAM6Isn6UTcLfQKkIDw==",
      "X-Amz-Cf-Pop": "IAD12-P4",
      "X-Cache": "Miss from cloudfront",
      "X-Device": "desktop/desktop",
      "X-Permitted-Cross-Domain-Policies": "none",
      "X-Served-By": "varnish-8578589cb6-htcts",
      "X-Varnish": "394780989 397194145",
      "X-XSS-Protection": "1; mode=block"
    },
    "status": 200,
    "url": "https://www.sueddeutsche.de/"
  },
  "meinung.html": {
    "date": "2022-10-01T02:52:45.275372",
    "headers": {
      "Accept-Ranges": "bytes",
      "Age": "94",
      "Cache-Control": "public, max-age=120",
      "Connection": "keep-alive",
      "Content-Security-Policy": "upgrade-insecure-requests",
      "Content-Type": "text/html; charset=UTF-8",
      "Date": "Sat, 01 Oct 2022 02:52:45 GMT",
      "Strict-Transport-Security": "max-age=31536000",
      "Transfer-Encoding": "chunked",
      "Vary": "Origin,Accept-Encoding",
      "Via": "1.1 varnish (Varnish/7.0), 1.1 a27022837959b6f70545c8d6d0de9d04.cloudfront.net (CloudFront)",
      "X-Amz-Cf-Id": "p_HS08MnsL5s9a7K6znaXhwVBl3hsxit5yiyYaUc8WqGv_iiOjAp3A==",
      "X-Amz-Cf-Pop": "IAD12-P4",
      "X-Cache": "Miss from cloudfront",
      "X-Device": "desktop/desktop",
      "X-Permitted-Cross-Domain-Policies": "none",
      "X-Served-By": "varnish-8578589cb6-xrpkd",
      "X-Varnish": "407589749 405918622",
      "X-XSS-Protection": "1; mode=block"
    },
    "status": 200,
    "url": "https://www.sueddeutsche.de/meinung"
  },
  "panorama.html": {
    "date": "2022-10-01T02:52:45.398194",
    "headers": {
      "Accept-Ranges": "bytes",
      "Age": "8",
      "Cache-Control": "public, max-age=120",
      "Connection": "keep-alive",
      "Content-Security-Policy": "upgrade-insecure-requests",
      "Content-Type": "text/html; charset=UTF-8",
      "Date": "Sat, 01 Oct 2022 02:52:45 GMT",
      "Strict-Transport-Security": "max-age=31536000",
      "Transfer-Encoding": "chunked",
      "Vary": "Origin,Accept-Encoding",
      "Via": "1.1 varnish (Varnish/7.0), 1.1 a27022837959b6f70545c8d6d0de9d04.cloudfront.net (CloudFront)",
      "X-Amz-Cf-Id": "hmk2trE9ud4jh5ST_kNqn_buw6Slq_jNqYXphzrPBUaxgLekPh9a_g==",
      "X-Amz-Cf-Pop": "IAD12-P4",
      "X-Cache": "Miss from cloudfront",
      "X-Device": "desktop/desktop",
      "X-Permitted-Cross-Domain-Policies": "none",
      "X-Served-By": "varnish-8578589cb6-htcts",
      "X-Varnish": "394781055 398754625",
      "X-XSS-Protection": "1; mode=block"
    },
    "status": 200,
    "url": "https://www.sueddeutsche.de/panorama"
  },
  "plus.html": {
    "date": "2022-10-01T02:52:44.306494",
    "headers": {
      "Accept-Ranges": "bytes",
      "Cache-Control": "public,max-age=300",
      "Connection": "keep-alive",
      "Content-Length": "112668",
      "Content-Type": "text/html",
      "Date": "Sat, 01 Oct 2022 02:52:45 GMT",
      "ETag": "\"4e90e4eaf43e072ef9ed0aa40638748b\"",
      "Last-Modified": "Sat, 01 Oct 2022 02:46:09 GMT",
      "Server": "AmazonS3",
      "Vary": "Accept-Encoding",
      "Via": "1.1 a27022837959b6f70545c8d6d0de9d04.cloudfront.net (CloudFront)",
      "X-Amz-Cf-Id": "pxgTc4wiPSegIIViYSFG5ui4dOQKKL9tFotpRos8hxL6di1RijfzfA==",
      "X-Amz-Cf-Pop": "IAD12-P4",
      "X-Cache": "RefreshHit from cloudfront"
    },
    "status": 200,
    "url": "https://plus.sueddeutsche.de/"
  },
  "politik.html": {
    "date": "2022-10-01T02:52:45.020656",
    "headers": {
      "Accept-Ranges": "bytes",
      "Age": "29",
      "Cache-Control": "public, max-age=120",
      "Connection": "keep-alive",
      "Content-Security-Policy": "upgrade-insecure-requests",
      "Content-Type": "text/html; charset=UTF-8",
      "Date": "Sat, 01 Oct 2022 02:52:45 GMT",
      "Strict-Transport-Security": "max-age=31536000",
      "Transfer-Encoding": "chunked",
      "Vary": "Origin,Accept-Encoding",
      "Via": "1.1 varnish (Varnish/7.0), 1.1 a27022837959b6f70545c8d6d0de9d04.cloudfront.net (CloudFront)",
      "X-Amz-Cf-Id": "OICE7OvhppA42imOPa9_Dy9W-LeuHcmB2I-kjmvSpRTJyZShYwdyFA==",
      "X-Amz-Cf-Pop": "IAD12-P4",
      "X-Cache": "Miss from cloudfront",
      "X-Device": "desktop/desktop",
      "X-Permitted-Cross-Domain-Policies": "none",
      "X-Served-By": "varnish-8578589cb6-xrpkd",
      "X-Varnish": "408781578 408168049",
      "X-XSS-Protection": "1; mode=block"
    },
    "status": 200,
    "url": "https://www.sueddeutsche.de/politik"
  },
  "sport.html": {
    "date": "2022-10-01T02:52:45.524740",
    "headers": {
      "Accept-Ranges": "bytes",
      "Age": "31",
      "Cache-Control": "public, max-age=120",
      "Connection": "keep-alive",
      "Content-Security-Policy": "upgrade-insecure-requests",
      "Content-Type": "text/html; charset=UTF-8",
      "Date": "Sat, 01 Oct 2022 02:52:45 GMT",
      "Strict-Transport-Security": "max-age=31536000",
      "Transfer-Encoding": "chunked",
      "Vary": "Origin,Accept-Encoding",
      "Via": "1.1 varnish (Varnish/7.0), 1.1 a27022837959b6f70545c8d6d0de9d04.cloudfront.net (CloudFront)",
      "X-Amz-Cf-Id": "AAhjn5KsauWMJJdu-fhSifhyztTpnkD-7AbJmkc-d0y6wHfACBM__w==",
      "X-Amz-Cf-Pop": "IAD12-P4",
      "X-Cache": "Miss from cloudfront",
      "X-Device": "desktop/desktop",
      "X-Permitted-Cross-Domain-Policies": "none",
      "X-Served-By": "varnish-8578589cb6-xrpkd",
      "X-Varnish": "407353053 407089549",
      "X-XSS-Protection": "1; mode=block"
    },
    "status": 200,
    "url": "https://www.sueddeutsche.de/sport"
  },
  "wirtschaft.html": {
    "date": "2022-10-01T02:52:45.152533",
    "headers": {
      "Accept-Ranges": "bytes",
      "Age": "126",
      "Cache-Control": "public, max-age=120",
      "Connection": "keep-alive",
      "Content-Security-Policy": "upgrade-insecure-requests",
      "Content-Type": "text/html; charset=UTF-8",
      "Date": "Sat, 01 Oct 2022 02:52:45 GMT",
      "Strict-Transport-Security": "max-age=31536000",
      "Transfer-Encoding": "chunked",
      "Vary": "Origin,Accept-Encoding",
      "Via": "1.1 varnish (Varnish/7.0), 1.1 a27022837959b6f70545c8d6d0de9d04.cloudfront.net (CloudFront)",
      "X-Amz-Cf-Id": "IIwdlqHL6-CUWL8vo_mgK7aQGXX-rbfkJpYjVCTocrPH_WtuasNsig==",
      "X-Amz-Cf-Pop": "IAD12-P4",
      "X-Cache": "Miss from cloudfront",
      "X-Device": "desktop/desktop",
      "X-Permitted-Cross-Domain-Policies": "none",
      "X-Served-By": "varnish-8578589cb6-xrpkd",
      "X-Varnish": "408425931 397725279",
      "X-XSS-Protection": "1; mode=block"
    },
    "status": 200,
    "url": "https://www.sueddeutsche.de/wirtschaft"
  }
}