{
  "impressum.html": {
    "date": "2026-02-01T01:29:45.683145",
    "headers": {
      "Accept-Ranges": "bytes",
      "Connection": "keep-alive",
      "Content-Length": "262983",
      "Content-Security-Policy": "default-src 'self'; img-src 'self' https://images.ctfassets.net https://assets.ctfassets.net; script-src 'self'; style-src 'self' 'unsafe-inline' https://assets.ctfassets.net; object-src 'self' https://assets.ctfassets.net; font-src 'self';",
      "Content-Type": "text/html",
      "Date": "Sun, 01 Feb 2026 01:29:47 GMT",
      "ETag": "\"de472ec9f8ae74773d7554859eaa26f3\"",
      "Last-Modified": "Wed, 28 Jan 2026 17:53:30 GMT",
      "Referrer-Policy": "same-origin",
      "Server": "AmazonS3",
      "Strict-Transport-Security": "max-age=31536000",
      "Via": "1.1 df843ecea619b6b3c300e731832f34a4.cloudfront.net (CloudFront)",
      "X-Amz-Cf-Id": "V2T7-SB4sr3Nb1YuDlfTW1L9PnCPz_WKBVmQ1OD-Z_tFCGsFtCezwQ==",
      "X-Amz-Cf-Pop": "DFW59-P2",
      "X-Cache": "RefreshHit from cloudfront",
      "X-Content-Type-Options": "nosniff",
      "X-Frame-Options": "DENY",
      "X-XSS-Protection": "1; mode=block",
      "x-amz-server-side-encryption": "AES256",
      "x-amz-version-id": "pITCjRxpWKPyTBwH4n5IKD_oJagjTeYX"
    },
    "status": 200,
    "url": "https://www.sueddeutsche.de/datenschutz"
  },
  "index.html": {
    "date": "2026-02-01T01:29:37.676244",
    "headers": {
      "Accept-Ranges": "bytes",
      "Age": "23",
      "Alt-Svc": "h3=\":443\"; ma=86400",
      "Cache-Control": "public,max-age=60,stale-if-error=86400",
      "Connection": "keep-alive",
      "Content-Security-Policy": "upgrade-insecure-requests;frame-ancestors 'self' https://*.sueddeutsche.de https://*.jetzt.de https://*.szcms.de https://*.szdm.io;",
      "Content-Type": "text/html; charset=utf-8",
      "Date": "Sun, 01 Feb 2026 01:29:38 GMT",
      "Strict-Transport-Security": "max-age=31536000",
      "Transfer-Encoding": "chunked",
      "Vary": "Accept-Encoding",
      "Via": "1.1 206f3b6a8991f0da5725b300de19e25e.cloudfront.net (CloudFront)",
      "X-Amz-Cf-Id": "SLlvxXfkNy06_pc95S28d2gRyJ-5TSNBgGcAs46b9NwH6-VD03Cpew==",
      "X-Amz-Cf-Pop": "PHX50-P1",
      "X-Cache": "Miss from cloudfront",
      "X-Permitted-Cross-Domain-Policies": "none",
      "X-Served-By": "szde",
      "X-XSS-Protection": "1; mode=block"
    },
    "status": 200,
    "url": "https://www.sueddeutsche.de/"
  },
  "meinung.html": {
    "date": "2026-02-01T01:29:42.166409",
    "headers": {
      "Accept-Ranges": "bytes",
      "Age": "28",
      "Alt-Svc": "h3=\":443\"; ma=86400",
      "Cache-Control": "public,max-age=60,stale-if-error=86400",
      "Connection": "keep-alive",
      "Content-Security-Policy": "upgrade-insecure-requests;frame-ancestors 'self' https://*.sueddeutsche.de https://*.jetzt.de https://*.szcms.de https://*.szdm.io;",
      "Content-Type": "text/html; charset=utf-8",
      "Date": "Sun, 01 Feb 2026 01:29:42 GMT",
      "Strict-Transport-Security": "max-age=31536000",
      "Transfer-Encoding": "chunked",
      "Vary": "Accept-Encoding",
      "Via": "1.1 206f3b6a8991f0da5725b300de19e25e.cloudfront.net (CloudFront)",
      "X-Amz-Cf-Id": "Ix6Nu1I7YjD9h1HrWBfPTiaENXBRaEqIdinNE32rfNdEJwYeb9IdAA==",
      "X-Amz-Cf-Pop": "PHX50-P1",
      "X-Cache": "Miss from cloudfront",
      "X-Permitted-Cross-Domain-Policies": "none",
      "X-Served-By": "szde",
      "X-XSS-Protection": "1; mode=block"
    },
    "status": 200,
    "url": "https://www.sueddeutsche.de/meinung"
  },
  "panorama.html": {
    "date": "2026-02-01T01:29:42.517818",
    "headers": {
      "Accept-Ranges": "bytes",
      "Age": "35",
      "Alt-Svc": "h3=\":443\"; ma=86400",
      "Cache-Control": "public,max-age=60,stale-if-error=86400",
      "Connection": "keep-alive",
      "Content-Security-Policy": "upgrade-insecure-requests;frame-ancestors 'self' https://*.sueddeutsche.de https://*.jetzt.de https://*.szcms.de https://*.szdm.io;",
      "Content-Type": "text/html; charset=utf-8",
      "Date": "Sun, 01 Feb 2026 01:29:42 GMT",
      "Strict-Transport-Security": "max-age=31536000",
      "Transfer-Encoding": "chunked",
      "Vary": "Accept-Encoding",
      "Via": "1.1 206f3b6a8991f0da5725b300de19e25e.cloudfront.net (CloudFront)",
      "X-Amz-Cf-Id": "lCu-sXTTijqhl4FdItIFlGBix1-QB8OLkywccrHLzBBZ79HSHSm5nA==",
      "X-Amz-Cf-Pop": "PHX50-P1",
      "X-Cache": "Miss from cloudfront",
      "X-Permitted-Cross-Domain-Policies": "none",
      "X-Served-By": "szde",
      "X-XSS-Protection": "1; mode=block"
    },
    "status": 200,
    "url": "https://www.sueddeutsche.de/panorama"
  },
  "plus.html": {
    "date": "2026-02-01T01:29:38.911409",
    "headers": {
      "Accept-Ranges": "bytes",
      "Age": "101",
      "Alt-Svc": "h3=\":443\"; ma=86400",
      "Cache-Control": "public,max-age=60,stale-if-error=86400",
      "Connection": "keep-alive",
      "Content-Security-Policy": "upgrade-insecure-requests;frame-ancestors 'self' https://*.sueddeutsche.de https://*.jetzt.de https://*.szcms.de https://*.szdm.io;",
      "Content-Type": "text/html; charset=utf-8",
      "Date": "Sun, 01 Feb 2026 01:29:39 GMT",
      "Strict-Transport-Security": "max-age=31536000",
      "Transfer-Encoding": "chunked",
      "Vary": "Accept-Encoding",
      "Via": "1.1 7d150f36635154864a915eba00666ce6.cloudfront.net (CloudFront)",
      "X-Amz-Cf-Id": "D5rM5BNgB0ENJxGccqrI9mldN4CgK89BTBb6bbI-dQzXNRl8XhqzUA==",
      "X-Amz-Cf-Pop": "PHX52-P1",
      "X-Cache": "Miss from cloudfront",
      "X-Permitted-Cross-Domain-Policies": "none",
      "X-Served-By": "szde",
      "X-XSS-Protection": "1; mode=block"
    },
    "status": 200,
    "url": "https://plus.sueddeutsche.de/"
  },
  "politik.html": {
    "date": "2026-02-01T01:29:40.991341",
    "headers": {
      "Accept-Ranges": "bytes",
      "Age": "43",
      "Alt-Svc": "h3=\":443\"; ma=86400",
      "Cache-Control": "public,max-age=60,stale-if-error=86400",
      "Connection": "keep-alive",
      "Content-Security-Policy": "upgrade-insecure-requests;frame-ancestors 'self' https://*.sueddeutsche.de https://*.jetzt.de https://*.szcms.de https://*.szdm.io;",
      "Content-Type": "text/html; charset=utf-8",
      "Date": "Sun, 01 Feb 2026 01:29:41 GMT",
      "Strict-Transport-Security": "max-age=31536000",
      "Transfer-Encoding": "chunked",
      "Vary": "Accept-Encoding",
      "Via": "1.1 206f3b6a8991f0da5725b300de19e25e.cloudfront.net (CloudFront)",
      "X-Amz-Cf-Id": "HigieGDRa4n8bSiCQx-7zQ30E8sz67OjZns_dpf9NDCi6ihtjYhUEw==",
      "X-Amz-Cf-Pop": "PHX50-P1",
      "X-Cache": "Miss from cloudfront",
      "X-Permitted-Cross-Domain-Policies": "none",
      "X-Served-By": "szde",
      "X-XSS-Protection": "1; mode=block"
    },
    "status": 200,
    "url": "https://www.sueddeutsche.de/politik"
  },
  "sport.html": {
    "date": "2026-02-01T01:29:42.854602",
    "headers": {
      "Accept-Ranges": "bytes",
      "Age": "37",
      "Alt-Svc": "h3=\":443\"; ma=86400",
      "Cache-Control": "public,max-age=60,stale-if-error=86400",
      "Connection": "keep-alive",
      "Content-Security-Policy": "upgrade-insecure-requests;frame-ancestors 'self' https://*.sueddeutsche.de https://*.jetzt.de https://*.szcms.de https://*.szdm.io;",
      "Content-Type": "text/html; charset=utf-8",
      "Date": "Sun, 01 Feb 2026 01:29:42 GMT",
      "Strict-Transport-Security": "max-age=31536000",
      "Transfer-Encoding": "chunked",
      "Vary": "Accept-Encoding",
      "Via": "1.1 206f3b6a8991f0da5725b300de19e25e.cloudfront.net (CloudFront)",
      "X-Amz-Cf-Id": "p4n_bCYMvy6YxaRqoRepoOwFD1xw8G2Agc--oTtKukTvx4nw1_Enag==",
      "X-Amz-Cf-Pop": "PHX50-P1",
      "X-Cache": "Miss from cloudfront",
      "X-Permitted-Cross-Domain-Policies": "none",
      "X-Served-By": "szde",
      "X-XSS-Protection": "1; mode=block"
    },
    "status": 200,
    "url": "https://www.sueddeutsche.de/sport"
  },
  "wirtschaft.html": {
    "date": "2026-02-01T01:29:41.674743",
    "headers": {
      "Accept-Ranges": "bytes",
      "Age": "20",
      "Alt-Svc": "h3=\":443\"; ma=86400",
      "Cache-Control": "public,max-age=60,stale-if-error=86400",
      "Connection": "keep-alive",
      "Content-Security-Policy": "upgrade-insecure-requests;frame-ancestors 'self' https://*.sueddeutsche.de https://*.jetzt.de https://*.szcms.de https://*.szdm.io;",
      "Content-Type": "text/html; charset=utf-8",
      "Date": "Sun, 01 Feb 2026 01:29:41 GMT",
      "Strict-Transport-Security": "max-age=31536000",
      "Transfer-Encoding": "chunked",
      "Vary": "Accept-Encoding",
      "Via": "1.1 206f3b6a8991f0da5725b300de19e25e.cloudfront.net (CloudFront)",
      "X-Amz-Cf-Id": "d9NViSpYnf_4rzQ6hisX5nijUqxAYYRTddnD6gBGmBt4Qw3rbn4HYQ==",
      "X-Amz-Cf-Pop": "PHX50-P1",
      "X-Cache": "Miss from cloudfront",
      "X-Permitted-Cross-Domain-Policies": "none",
      "X-Served-By": "szde",
      "X-XSS-Protection": "1; mode=block"
    },
    "status": 200,
    "url": "https://www.sueddeutsche.de/wirtschaft"
  }
}