{
  "ausland": {
    "date": "2026-03-01T01:27:51.374200",
    "headers": {
      "Access-Control-Expose-Headers": "Server-Timing",
      "Cache-Control": "no-cache, must-revalidate, max-age=10",
      "Connection": "keep-alive, Transfer-Encoding",
      "Content-Security-Policy": "upgrade-insecure-requests",
      "Content-Type": "text/html; charset=utf-8",
      "Date": "Sun, 01 Mar 2026 01:27:51 GMT",
      "ETag": "W/\"2e4cd-xffQEu0XaKsPZ7+4FkX7EiiaKAU\"",
      "Expect-CT": "max-age=0",
      "Last-Modified": "Sat, 28 Feb 2026 20:33:16 GMT",
      "Server": "Apache",
      "Server-Timing": "traceparent;desc=\"00-696c3d20d64f774123faee5c7f536e81-2462760be2d2cefa-01\"",
      "Strict-Transport-Security": "max-age=15552000; includeSubDomains",
      "Transfer-Encoding": "chunked",
      "Vary": "Accept-Encoding, x-va-bild-pur, x-va-adfree, x-va-bildplus, Origin",
      "X-CM-Host": "www.bild.de",
      "X-CM-Uri": "/news/ausland/news-ausland/home-15681774.bild.html",
      "X-Content-Type-Options": "nosniff",
      "X-DNS-Prefetch-Control": "off",
      "X-Download-Options": "noopen",
      "X-Permitted-Cross-Domain-Policies": "none",
      "X-Refresh": "s=XXX|h=1|c=|t=19.439|a=19.164|rd=Sun, 01 Mar 2026 01:27:31 GMT|dd=Sun, 01 Mar 2026 01:27:51 GMT",
      "X-UA-Compatible": "IE=Edge",
      "X-XSS-Protection": "0"
    },
    "status": 200,
    "url": "https://www.bild.de/news/ausland/news-ausland/home-15681774.bild.html"
  },
  "ausland2": {
    "date": "2026-03-01T01:27:52.804407",
    "headers": {
      "Access-Control-Expose-Headers": "Server-Timing",
      "Cache-Control": "no-cache, must-revalidate, max-age=10",
      "Connection": "keep-alive, Transfer-Encoding",
      "Content-Security-Policy": "upgrade-insecure-requests",
      "Content-Type": "text/html; charset=utf-8",
      "Date": "Sun, 01 Mar 2026 01:27:53 GMT",
      "ETag": "W/\"2f8d5-Jal3fjMWlWTUaZoz8tpQNbfpajw\"",
      "Expect-CT": "max-age=0",
      "Last-Modified": "Sun, 01 Mar 2026 01:13:28 GMT",
      "Server": "Apache",
      "Server-Timing": "traceparent;desc=\"00-d3d88c80d4c0352b371bf5d1808a5820-77662dfc70ce90e3-01\"",
      "Strict-Transport-Security": "max-age=15552000; includeSubDomains",
      "Transfer-Encoding": "chunked",
      "Vary": "Accept-Encoding, x-va-bild-pur, x-va-adfree, x-va-bildplus, Origin",
      "X-CM-Host": "www.bild.de",
      "X-CM-Uri": "/politik/ausland/politik-ausland/home-15683414.bild.html",
      "X-Content-Type-Options": "nosniff",
      "X-DNS-Prefetch-Control": "off",
      "X-Download-Options": "noopen",
      "X-Permitted-Cross-Domain-Policies": "none",
      "X-Refresh": "s=XXX|h=2|c=|t=19.825|a=19.304|rd=Sun, 01 Mar 2026 01:27:33 GMT|dd=Sun, 01 Mar 2026 01:27:53 GMT",
      "X-UA-Compatible": "IE=Edge",
      "X-XSS-Protection": "0"
    },
    "status": 200,
    "url": "https://www.bild.de/politik/ausland/politik-ausland/home-15683414.bild.html"
  },
  "auto": {
    "date": "2026-03-01T01:27:50.689510",
    "headers": {
      "Access-Control-Expose-Headers": "Server-Timing",
      "Cache-Control": "no-cache, must-revalidate, max-age=10",
      "Connection": "keep-alive, Transfer-Encoding",
      "Content-Security-Policy": "upgrade-insecure-requests",
      "Content-Type": "text/html; charset=utf-8",
      "Date": "Sun, 01 Mar 2026 01:27:51 GMT",
      "ETag": "W/\"3c539-SESGFLY3BH1pTcbr1PWTOLS/r9A\"",
      "Expect-CT": "max-age=0",
      "Last-Modified": "Sat, 28 Feb 2026 16:27:48 GMT",
      "Server": "Apache",
      "Server-Timing": "traceparent;desc=\"00-50de8163220650b9bb4f3da9f5d571ad-d46cc29809115d63-01\"",
      "Strict-Transport-Security": "max-age=15552000; includeSubDomains",
      "Transfer-Encoding": "chunked",
      "Vary": "Accept-Encoding, x-va-bild-pur, x-va-adfree, x-va-bildplus, Origin",
      "X-CM-Host": "www.bild.de",
      "X-CM-Uri": "/auto/startseite/auto/auto-home-15478182.bild.html",
      "X-Content-Type-Options": "nosniff",
      "X-DNS-Prefetch-Control": "off",
      "X-Download-Options": "noopen",
      "X-Permitted-Cross-Domain-Policies": "none",
      "X-Refresh": "s=XXX|h=4|c=|t=19.310|a=16.934|rd=Sun, 01 Mar 2026 01:27:33 GMT|dd=Sun, 01 Mar 2026 01:27:50 GMT",
      "X-UA-Compatible": "IE=Edge",
      "X-XSS-Protection": "0"
    },
    "status": 200,
    "url": "https://www.bild.de/auto/startseite/auto/auto-home-15478182.bild.html"
  },
  "auto2": {
    "date": "2026-03-01T01:27:54.831864",
    "headers": {
      "Cache-Control": "s-maxage=600, max-age=600",
      "Connection": "keep-alive, Transfer-Encoding",
      "Content-Security-Policy": "upgrade-insecure-requests",
      "Content-Type": "text/html; charset=UTF-8",
      "Date": "Sun, 01 Mar 2026 01:27:55 GMT",
      "Link": "<https://www.bild.de/kaufberater/wp-json/>; rel=\"https://api.w.org/\", <https://www.bild.de/kaufberater/wp-json/wp/v2/categories/238>; rel=\"alternate\"; title=\"JSON\"; type=\"application/json\"",
      "Referrer-Policy": "strict-origin-when-cross-origin",
      "Server": "Apache",
      "Strict-Transport-Security": "max-age=31536000; includeSubDomains; preload",
      "Transfer-Encoding": "chunked",
      "Vary": "Accept-Encoding, Origin",
      "X-Content-Type-Options": "nosniff",
      "X-Frame-Options": "SAMEORIGIN",
      "X-Refresh": "s=XXX|h=0|c=|t=463.000|a=163.000|rd=Sun, 01 Mar 2026 01:25:11 GMT|dd=Sun, 01 Mar 2026 01:27:54 GMT",
      "X-UA-Compatible": "IE=Edge",
      "X-XSS-Protection": "1; mode=block"
    },
    "status": 200,
    "url": "https://www.bild.de/kaufberater/auto/"
  },
  "auto3": {
    "date": "2026-03-01T01:27:57.888798",
    "headers": {
      "Access-Control-Expose-Headers": "Server-Timing",
      "Cache-Control": "no-cache, must-revalidate, max-age=10",
      "Connection": "keep-alive, Transfer-Encoding",
      "Content-Security-Policy": "upgrade-insecure-requests",
      "Content-Type": "text/html; charset=utf-8",
      "Date": "Sun, 01 Mar 2026 01:27:58 GMT",
      "ETag": "W/\"343d7-AbWyhzWw7vxcbaohMQS+IdeGM/U\"",
      "Expect-CT": "max-age=0",
      "Last-Modified": "Sat, 28 Feb 2026 16:27:48 GMT",
      "Server": "Apache",
      "Server-Timing": "traceparent;desc=\"00-c8776b7df6c49a7f91d9c952ead93aae-40dbd0c2dfe65ed8-01\"",
      "Strict-Transport-Security": "max-age=15552000; includeSubDomains",
      "Transfer-Encoding": "chunked",
      "Vary": "Accept-Encoding, x-va-bild-pur, x-va-adfree, x-va-bildplus, Origin",
      "X-CM-Host": "m.bild.de",
      "X-CM-Uri": "/auto/startseite/auto/auto-home-15478182.bildMobile.html",
      "X-Content-Type-Options": "nosniff",
      "X-DNS-Prefetch-Control": "off",
      "X-Download-Options": "noopen",
      "X-Permitted-Cross-Domain-Policies": "none",
      "X-Refresh": "s=XXX|h=0|c=|t=19.922|a=0.000|rd=Sun, 01 Mar 2026 01:27:58 GMT|dd=Sun, 01 Mar 2026 01:27:58 GMT",
      "X-UA-Compatible": "IE=Edge",
      "X-XSS-Protection": "0"
    },
    "status": 200,
    "url": "https://m.bild.de/auto/startseite/auto/auto-home-15478182.bildMobile.html"
  },
  "datenschutz": {
    "date": "2026-03-01T01:27:58.562427",
    "headers": {
      "Access-Control-Expose-Headers": "Server-Timing",
      "Cache-Control": "no-cache, must-revalidate, max-age=10",
      "Connection": "keep-alive, Transfer-Encoding",
      "Content-Security-Policy": "upgrade-insecure-requests",
      "Content-Type": "text/html; charset=utf-8",
      "Date": "Sun, 01 Mar 2026 01:27:58 GMT",
      "ETag": "W/\"8ed6e-XjZSrYP1bQqQYdnqU3uK6qYo8FU\"",
      "Expect-CT": "max-age=0",
      "Last-Modified": "Mon, 09 Feb 2026 15:02:03 GMT",
      "Server": "Apache",
      "Server-Timing": "traceparent;desc=\"00-b9fa735dcc75d845c3c3ace0194f7329-93f6ad83b5b5930e-01\"",
      "Strict-Transport-Security": "max-age=15552000; includeSubDomains",
      "Transfer-Encoding": "chunked",
      "Vary": "Accept-Encoding, Origin",
      "X-CM-Host": "www.bild.de",
      "X-CM-Uri": "/corporate/site/datenschutz/artikel-datenschutz-54485502.bild.html",
      "X-Content-Type-Options": "nosniff",
      "X-DNS-Prefetch-Control": "off",
      "X-Download-Options": "noopen",
      "X-Permitted-Cross-Domain-Policies": "none",
      "X-Refresh": "s=XXX|h=2|c=|t=299.656|a=232.336|rd=Sun, 01 Mar 2026 01:24:06 GMT|dd=Sun, 01 Mar 2026 01:27:58 GMT",
      "X-UA-Compatible": "IE=Edge",
      "X-XSS-Protection": "0"
    },
    "status": 200,
    "url": "https://www.bild.de/corporate-site/datenschutz/datenschutz/artikel-datenschutz-54485502.bild.html"
  },
  "einherzfrkinder": {
    "date": "2026-03-01T01:27:52.058978",
    "headers": {
      "Access-Control-Expose-Headers": "Server-Timing",
      "Cache-Control": "no-cache, must-revalidate, max-age=10",
      "Connection": "keep-alive, Transfer-Encoding",
      "Content-Security-Policy": "upgrade-insecure-requests",
      "Content-Type": "text/html; charset=utf-8",
      "Date": "Sun, 01 Mar 2026 01:27:52 GMT",
      "ETag": "W/\"2fd8e-DynslVJ8aVoSQQRCIjt22ULOMV8\"",
      "Expect-CT": "max-age=0",
      "Last-Modified": "Fri, 13 Feb 2026 08:33:28 GMT",
      "Server": "Apache",
      "Server-Timing": "traceparent;desc=\"00-48b823fcd664c7331c4a60e01ba03f2f-798eaf9e040ff836-01\"",
      "Strict-Transport-Security": "max-age=15552000; includeSubDomains",
      "Transfer-Encoding": "chunked",
      "Vary": "Accept-Encoding",
      "X-CM-Host": "www.bild.de",
      "X-CM-Uri": "/news/einherzfuerkinder/ein-herz-fuer-kinder/home-15682108.bild.html",
      "X-Content-Type-Options": "nosniff",
      "X-DNS-Prefetch-Control": "off",
      "X-Download-Options": "noopen",
      "X-Permitted-Cross-Domain-Policies": "none",
      "X-Refresh": "s=XXX|h=0|c=|t=19.438|a=0.000|rd=Sat, 21 Feb 2026 16:28:37 GMT|dd=Sat, 21 Feb 2026 16:28:38 GMT",
      "X-UA-Compatible": "IE=Edge",
      "X-XSS-Protection": "0"
    },
    "status": 200,
    "url": "https://www.bild.de/news/einherzfuerkinder/ein-herz-fuer-kinder/home-15682108.bild.html"
  },
  "fussball": {
    "date": "2026-03-01T01:27:49.431084",
    "headers": {
      "Access-Control-Expose-Headers": "Server-Timing",
      "Cache-Control": "no-cache, must-revalidate, max-age=10",
      "Connection": "keep-alive, Transfer-Encoding",
      "Content-Security-Policy": "upgrade-insecure-requests",
      "Content-Type": "text/html; charset=utf-8",
      "Date": "Sun, 01 Mar 2026 01:27:49 GMT",
      "ETag": "W/\"65a19-mfwkXgkv9vvyPGY9snY5Rg+Hsj8\"",
      "Expect-CT": "max-age=0",
      "Last-Modified": "Sat, 28 Feb 2026 22:23:51 GMT",
      "Server": "Apache",
      "Server-Timing": "traceparent;desc=\"00-26b0644592f05179baf737cd57fb5267-25b4a249415b2161-01\"",
      "Strict-Transport-Security": "max-age=15552000; includeSubDomains",
      "Transfer-Encoding": "chunked",
      "Vary": "Accept-Encoding, x-va-bild-pur, x-va-adfree, x-va-bildplus, Origin",
      "X-CM-Host": "www.bild.de",
      "X-CM-Uri": "/sport/fussball/fussball/home-15769054.bild.html",
      "X-Content-Type-Options": "nosniff",
      "X-DNS-Prefetch-Control": "off",
      "X-Download-Options": "noopen",
      "X-Permitted-Cross-Domain-Policies": "none",
      "X-Refresh": "s=XXX|h=0|c=|t=19.903|a=0.000|rd=Sat, 28 Feb 2026 23:38:21 GMT|dd=Sat, 28 Feb 2026 23:38:21 GMT",
      "X-UA-Compatible": "IE=Edge",
      "X-XSS-Protection": "0"
    },
    "status": 200,
    "url": "https://www.bild.de/sport/fussball/fussball/home-15769054.bild.html"
  },
  "geldwirtschaft": {
    "date": "2026-03-01T01:27:55.464458",
    "headers": {
      "Access-Control-Expose-Headers": "Server-Timing",
      "Cache-Control": "no-cache, must-revalidate, max-age=10",
      "Connection": "keep-alive, Transfer-Encoding",
      "Content-Security-Policy": "upgrade-insecure-requests",
      "Content-Type": "text/html; charset=utf-8",
      "Date": "Sun, 01 Mar 2026 01:27:56 GMT",
      "ETag": "W/\"415d0-TGo2LFO6VKa0JzchwzhiNM6Y2Yg\"",
      "Expect-CT": "max-age=0",
      "Last-Modified": "Sat, 28 Feb 2026 16:33:45 GMT",
      "Server": "Apache",
      "Server-Timing": "traceparent;desc=\"00-106a035d12fcc0d6188228305192bdfb-f92f03534edb4a99-01\"",
      "Strict-Transport-Security": "max-age=15552000; includeSubDomains",
      "Transfer-Encoding": "chunked",
      "Vary": "Accept-Encoding, Origin",
      "X-CM-Host": "m.bild.de",
      "X-CM-Uri": "/leben-gesellschaft/mein-geld-finanzportal/alle-news-HpYSOPoVPZOkw3Mm7LLK",
      "X-Content-Type-Options": "nosniff",
      "X-DNS-Prefetch-Control": "off",
      "X-Download-Options": "noopen",
      "X-Permitted-Cross-Domain-Policies": "none",
      "X-Refresh": "s=XXX|h=1|c=|t=20.000|a=48.832|rd=Sun, 01 Mar 2026 01:27:07 GMT|dd=Sun, 01 Mar 2026 01:27:56 GMT",
      "X-UA-Compatible": "IE=Edge",
      "X-XSS-Protection": "0"
    },
    "status": 200,
    "url": "https://m.bild.de/geld/startseite/geld/geld-15683376.bildMobile.html"
  },
  "gesundheit": {
    "date": "2026-03-01T01:27:50.282400",
    "headers": {
      "Access-Control-Expose-Headers": "Server-Timing",
      "Cache-Control": "no-cache, must-revalidate, max-age=10",
      "Connection": "keep-alive, Transfer-Encoding",
      "Content-Security-Policy": "upgrade-insecure-requests",
      "Content-Type": "text/html; charset=utf-8",
      "Date": "Sun, 01 Mar 2026 01:27:50 GMT",
      "ETag": "W/\"53ec5-pMTwnEXMmv44YAkpW2Vk0MJahKg\"",
      "Expect-CT": "max-age=0",
      "Last-Modified": "Sat, 28 Feb 2026 11:33:10 GMT",
      "Server": "Apache",
      "Server-Timing": "traceparent;desc=\"00-d32b391818d5687560139b798b88e0af-4036263f9f69c18c-01\"",
      "Strict-Transport-Security": "max-age=15552000; includeSubDomains",
      "Transfer-Encoding": "chunked",
      "Vary": "Accept-Encoding, x-va-bild-pur, x-va-adfree, x-va-bildplus, Origin",
      "X-CM-Host": "www.bild.de",
      "X-CM-Uri": "/ratgeber/gesundheit/gesundheit/home-15734752.bild.html",
      "X-Content-Type-Options": "nosniff",
      "X-DNS-Prefetch-Control": "off",
      "X-Download-Options": "noopen",
      "X-Permitted-Cross-Domain-Policies": "none",
      "X-Refresh": "s=XXX|h=2|c=|t=20.000|a=0.912|rd=Sat, 28 Feb 2026 16:47:22 GMT|dd=Sat, 28 Feb 2026 16:47:23 GMT",
      "X-UA-Compatible": "IE=Edge",
      "X-XSS-Protection": "0"
    },
    "status": 200,
    "url": "https://www.bild.de/ratgeber/gesundheit/gesundheit/home-15734752.bild.html"
  },
  "impressum": {
    "date": "2026-03-01T01:27:58.372873",
    "headers": {
      "Access-Control-Expose-Headers": "Server-Timing",
      "Cache-Control": "no-cache, must-revalidate, max-age=10",
      "Connection": "keep-alive, Transfer-Encoding",
      "Content-Security-Policy": "upgrade-insecure-requests",
      "Content-Type": "text/html; charset=utf-8",
      "Date": "Sun, 01 Mar 2026 01:27:58 GMT",
      "ETag": "W/\"16228-g3+zQaJapfiUjclTZeDqUPeaVZo\"",
      "Expect-CT": "max-age=0",
      "Last-Modified": "Fri, 13 Dec 2024 11:04:27 GMT",
      "Server": "Apache",
      "Server-Timing": "traceparent;desc=\"00-53c3b5b7fa295d4a6107520723db1210-486cf2be2731758d-01\"",
      "Strict-Transport-Security": "max-age=15552000; includeSubDomains",
      "Transfer-Encoding": "chunked",
      "Vary": "Accept-Encoding, Origin",
      "X-CM-Host": "www.bild.de",
      "X-CM-Uri": "/corporate/site/bild-de/impressum-81395212.bild.html",
      "X-Content-Type-Options": "nosniff",
      "X-DNS-Prefetch-Control": "off",
      "X-Download-Options": "noopen",
      "X-Permitted-Cross-Domain-Policies": "none",
      "X-Refresh": "s=XXX|h=155|c=|t=21600.000|a=7469.751|rd=Sat, 28 Feb 2026 23:23:28 GMT|dd=Sun, 01 Mar 2026 01:27:58 GMT",
      "X-UA-Compatible": "IE=Edge",
      "X-XSS-Protection": "0"
    },
    "status": 200,
    "url": "https://www.bild.de/corporate/site/bild-de/impressum-81395212.bild.html"
  },
  "index.html": {
    "date": "2026-03-01T01:27:46.338171",
    "headers": {
      "Access-Control-Expose-Headers": "Server-Timing",
      "Cache-Control": "no-cache, must-revalidate, max-age=10",
      "Connection": "keep-alive, Transfer-Encoding",
      "Content-Security-Policy": "upgrade-insecure-requests",
      "Content-Type": "text/html; charset=utf-8",
      "Date": "Sun, 01 Mar 2026 01:27:46 GMT",
      "ETag": "W/\"b86a6-7bBeHf8E5Mlhw36rZlgFZGpRA/A\"",
      "Expect-CT": "max-age=0",
      "Last-Modified": "Sun, 01 Mar 2026 01:22:52 GMT",
      "Server": "Apache",
      "Server-Timing": "traceparent;desc=\"00-6c6218ed7113c74181788ad11fe83bca-23c71bd77fbf8a7d-01\"",
      "Strict-Transport-Security": "max-age=15552000; includeSubDomains",
      "Transfer-Encoding": "chunked",
      "Vary": "Accept-Encoding, x-va-bild-pur, x-va-adfree, x-va-bildplus, Origin",
      "X-CM-Host": "www.bild.de",
      "X-CM-Uri": "/",
      "X-Content-Type-Options": "nosniff",
      "X-DNS-Prefetch-Control": "off",
      "X-Download-Options": "noopen",
      "X-Permitted-Cross-Domain-Policies": "none",
      "X-Refresh": "s=XXX|h=47|c=|t=20.000|a=10.274|rd=Sun, 01 Mar 2026 01:25:29 GMT|dd=Sun, 01 Mar 2026 01:25:39 GMT",
      "X-UA-Compatible": "IE=Edge",
      "X-XSS-Protection": "0"
    },
    "status": 200,
    "url": "https://www.bild.de"
  },
  "inland": {
    "date": "2026-03-01T01:27:51.031970",
    "headers": {
      "Access-Control-Expose-Headers": "Server-Timing",
      "Cache-Control": "no-cache, must-revalidate, max-age=10",
      "Connection": "keep-alive, Transfer-Encoding",
      "Content-Security-Policy": "upgrade-insecure-requests",
      "Content-Type": "text/html; charset=utf-8",
      "Date": "Sun, 01 Mar 2026 01:27:51 GMT",
      "ETag": "W/\"2f61f-9AmYCYgApPwybb1k8NS3DH2sETE\"",
      "Expect-CT": "max-age=0",
      "Last-Modified": "Sat, 28 Feb 2026 22:05:01 GMT",
      "Server": "Apache",
      "Server-Timing": "traceparent;desc=\"00-d222ed6b159e3b770bb721fb3a6fa054-6f986c41f1a733b8-01\"",
      "Strict-Transport-Security": "max-age=15552000; includeSubDomains",
      "Transfer-Encoding": "chunked",
      "Vary": "Accept-Encoding, x-va-bild-pur, x-va-adfree, x-va-bildplus, Origin",
      "X-CM-Host": "www.bild.de",
      "X-CM-Uri": "/news/inland/news-inland/home-15665814.bild.html",
      "X-Content-Type-Options": "nosniff",
      "X-DNS-Prefetch-Control": "off",
      "X-Download-Options": "noopen",
      "X-Permitted-Cross-Domain-Policies": "none",
      "X-Refresh": "s=XXX|h=1|c=|t=19.532|a=11.168|rd=Sun, 01 Mar 2026 01:27:39 GMT|dd=Sun, 01 Mar 2026 01:27:51 GMT",
      "X-UA-Compatible": "IE=Edge",
      "X-XSS-Protection": "0"
    },
    "status": 200,
    "url": "https://www.bild.de/news/inland/news-inland/home-15665814.bild.html"
  },
  "inland2": {
    "date": "2026-03-01T01:27:52.422963",
    "headers": {
      "Access-Control-Expose-Headers": "Server-Timing",
      "Cache-Control": "no-cache, must-revalidate, max-age=10",
      "Connection": "keep-alive, Transfer-Encoding",
      "Content-Security-Policy": "upgrade-insecure-requests",
      "Content-Type": "text/html; charset=utf-8",
      "Date": "Sun, 01 Mar 2026 01:27:52 GMT",
      "ETag": "W/\"2e3be-wsb1iog4nR+maAjyhq5RIsRNZOg\"",
      "Expect-CT": "max-age=0",
      "Last-Modified": "Sat, 28 Feb 2026 18:34:30 GMT",
      "Server": "Apache",
      "Server-Timing": "traceparent;desc=\"00-7f99fd96da774d380cd6f931a27b51dc-bafa905d9c4e69ec-01\"",
      "Strict-Transport-Security": "max-age=15552000; includeSubDomains",
      "Transfer-Encoding": "chunked",
      "Vary": "Accept-Encoding, x-va-bild-pur, x-va-adfree, x-va-bildplus, Origin",
      "X-CM-Host": "www.bild.de",
      "X-CM-Uri": "/politik/inland/politik-inland/home-15682786.bild.html",
      "X-Content-Type-Options": "nosniff",
      "X-DNS-Prefetch-Control": "off",
      "X-Download-Options": "noopen",
      "X-Permitted-Cross-Domain-Policies": "none",
      "X-Refresh": "s=XXX|h=1|c=|t=20.000|a=0.112|rd=Sun, 01 Mar 2026 01:27:52 GMT|dd=Sun, 01 Mar 2026 01:27:52 GMT",
      "X-UA-Compatible": "IE=Edge",
      "X-XSS-Protection": "0"
    },
    "status": 200,
    "url": "https://www.bild.de/politik/inland/politik-inland/home-15682786.bild.html"
  },
  "kino": {
    "date": "2026-03-01T01:27:54.104398",
    "headers": {
      "Access-Control-Expose-Headers": "Server-Timing",
      "Cache-Control": "no-cache, must-revalidate, max-age=10",
      "Connection": "keep-alive, Transfer-Encoding",
      "Content-Security-Policy": "upgrade-insecure-requests",
      "Content-Type": "text/html; charset=utf-8",
      "Date": "Sun, 01 Mar 2026 01:27:54 GMT",
      "ETag": "W/\"3575a-w2XlSh/XTSPfR/TL8uiWErhMSM0\"",
      "Expect-CT": "max-age=0",
      "Last-Modified": "Fri, 27 Feb 2026 14:05:11 GMT",
      "Server": "Apache",
      "Server-Timing": "traceparent;desc=\"00-09cf944f8796ccd019518d2adfe3f1cd-84f99950015e95ae-01\"",
      "Strict-Transport-Security": "max-age=15552000; includeSubDomains",
      "Transfer-Encoding": "chunked",
      "Vary": "Accept-Encoding, x-va-bild-pur, x-va-adfree, x-va-bildplus, Origin",
      "X-CM-Host": "www.bild.de",
      "X-CM-Uri": "/unterhaltung/kino/kino/home-15697512.bild.html",
      "X-Content-Type-Options": "nosniff",
      "X-DNS-Prefetch-Control": "off",
      "X-Download-Options": "noopen",
      "X-Permitted-Cross-Domain-Policies": "none",
      "X-Refresh": "s=XXX|h=1|c=|t=19.250|a=13.166|rd=Sun, 01 Mar 2026 01:27:40 GMT|dd=Sun, 01 Mar 2026 01:27:54 GMT",
      "X-UA-Compatible": "IE=Edge",
      "X-XSS-Protection": "0"
    },
    "status": 200,
    "url": "https://www.bild.de/unterhaltung/kino/kino/home-15697512.bild.html"
  },
  "kommentareundkolumnen": {
    "date": "2026-03-01T01:27:53.378937",
    "headers": {
      "Access-Control-Expose-Headers": "Server-Timing",
      "Cache-Control": "no-cache, must-revalidate, max-age=10",
      "Connection": "keep-alive, Transfer-Encoding",
      "Content-Security-Policy": "upgrade-insecure-requests",
      "Content-Type": "text/html; charset=utf-8",
      "Date": "Sun, 01 Mar 2026 01:27:53 GMT",
      "ETag": "W/\"2e4f9-rTucsdrd73WGcWFPWwBQ3U6dPzg\"",
      "Expect-CT": "max-age=0",
      "Last-Modified": "Sat, 28 Feb 2026 10:35:06 GMT",
      "Server": "Apache",
      "Server-Timing": "traceparent;desc=\"00-125a409076aca9a6fb57bdc6e1b3c764-542456490406ddbd-01\"",
      "Strict-Transport-Security": "max-age=15552000; includeSubDomains",
      "Transfer-Encoding": "chunked",
      "Vary": "Accept-Encoding, x-va-bild-pur, x-va-adfree, x-va-bildplus, Origin",
      "X-CM-Host": "www.bild.de",
      "X-CM-Uri": "/home/hot-on-bild/bild-kommentar/kommentare-meinungen-und-kolumnen-zu-aktuellen-themen-35874522.bild.html",
      "X-Content-Type-Options": "nosniff",
      "X-DNS-Prefetch-Control": "off",
      "X-Download-Options": "noopen",
      "X-Permitted-Cross-Domain-Policies": "none",
      "X-Refresh": "s=XXX|h=1|c=|t=20.000|a=0.111|rd=Sun, 01 Mar 2026 01:27:53 GMT|dd=Sun, 01 Mar 2026 01:27:53 GMT",
      "X-UA-Compatible": "IE=Edge",
      "X-XSS-Protection": "0"
    },
    "status": 200,
    "url": "https://www.bild.de/home/hot-on-bild/bild-kommentar/kommentare-meinungen-und-kolumnen-zu-aktuellen-themen-35874522.bild.html"
  },
  "lifestyle": {
    "date": "2026-03-01T01:27:57.219011",
    "headers": {
      "Access-Control-Expose-Headers": "Server-Timing",
      "Cache-Control": "no-cache, must-revalidate, max-age=10",
      "Connection": "keep-alive, Transfer-Encoding",
      "Content-Security-Policy": "upgrade-insecure-requests",
      "Content-Type": "text/html; charset=utf-8",
      "Date": "Sun, 01 Mar 2026 01:27:57 GMT",
      "ETag": "W/\"3e34b-Is96PK6wRui/LYZN3u5c4j6fLHk\"",
      "Expect-CT": "max-age=0",
      "Last-Modified": "Sat, 28 Feb 2026 17:01:49 GMT",
      "Server": "Apache",
      "Server-Timing": "traceparent;desc=\"00-828ab12b1bf79e150659a02acc3ad98e-5ac1e32e1475327e-01\"",
      "Strict-Transport-Security": "max-age=15552000; includeSubDomains",
      "Transfer-Encoding": "chunked",
      "Vary": "Accept-Encoding, x-va-bild-pur, x-va-adfree, x-va-bildplus, Origin",
      "X-CM-Host": "www.bild.de",
      "X-CM-Uri": "/lifestyle/startseite/lifestyle/lifestyle-15478526.bild.html",
      "X-Content-Type-Options": "nosniff",
      "X-DNS-Prefetch-Control": "off",
      "X-Download-Options": "noopen",
      "X-Permitted-Cross-Domain-Policies": "none",
      "X-Refresh": "s=XXX|h=0|c=|t=19.919|a=0.000|rd=Sun, 01 Mar 2026 01:27:57 GMT|dd=Sun, 01 Mar 2026 01:27:57 GMT",
      "X-UA-Compatible": "IE=Edge",
      "X-XSS-Protection": "0"
    },
    "status": 200,
    "url": "https://www.bild.de/lifestyle/startseite/lifestyle/lifestyle-15478526.bild.html"
  },
  "mystery": {
    "date": "2026-03-01T01:27:51.716613",
    "headers": {
      "Access-Control-Expose-Headers": "Server-Timing",
      "Cache-Control": "no-cache, must-revalidate, max-age=10",
      "Connection": "keep-alive, Transfer-Encoding",
      "Content-Security-Policy": "upgrade-insecure-requests",
      "Content-Type": "text/html; charset=utf-8",
      "Date": "Sun, 01 Mar 2026 01:27:52 GMT",
      "ETag": "W/\"2f050-geRsl8hKOeh6YQUHf3xvY5jpvgA\"",
      "Expect-CT": "max-age=0",
      "Last-Modified": "Sat, 28 Feb 2026 21:14:30 GMT",
      "Server": "Apache",
      "Server-Timing": "traceparent;desc=\"00-6f3004963ec74f932af82ccf63483e6c-93ba4af3e5b5a4ff-01\"",
      "Strict-Transport-Security": "max-age=15552000; includeSubDomains",
      "Transfer-Encoding": "chunked",
      "Vary": "Accept-Encoding, x-va-bild-pur, x-va-adfree, x-va-bildplus, Origin",
      "X-CM-Host": "www.bild.de",
      "X-CM-Uri": "/news/mystery-themen/mystery/home-15682164.bild.html",
      "X-Content-Type-Options": "nosniff",
      "X-DNS-Prefetch-Control": "off",
      "X-Download-Options": "noopen",
      "X-Permitted-Cross-Domain-Policies": "none",
      "X-Refresh": "s=XXX|h=0|c=|t=19.888|a=0.000|rd=Sun, 01 Mar 2026 01:27:51 GMT|dd=Sun, 01 Mar 2026 01:27:51 GMT",
      "X-UA-Compatible": "IE=Edge",
      "X-XSS-Protection": "0"
    },
    "status": 200,
    "url": "https://www.bild.de/news/mystery-themen/mystery/home-15682164.bild.html"
  },
  "news": {
    "date": "2026-03-01T01:27:47.052076",
    "headers": {
      "Access-Control-Expose-Headers": "Server-Timing",
      "Cache-Control": "no-cache, must-revalidate, max-age=10",
      "Connection": "keep-alive, Transfer-Encoding",
      "Content-Security-Policy": "upgrade-insecure-requests",
      "Content-Type": "text/html; charset=utf-8",
      "Date": "Sun, 01 Mar 2026 01:27:47 GMT",
      "ETag": "W/\"3de0a-Sdep+3FXRM02FYRp0Wg+f+VC7oo\"",
      "Expect-CT": "max-age=0",
      "Last-Modified": "Sat, 28 Feb 2026 22:00:50 GMT",
      "Server": "Apache",
      "Server-Timing": "traceparent;desc=\"00-30aa3c562c1317d1a773f75549ae127c-29d00d66fac30abe-01\"",
      "Strict-Transport-Security": "max-age=15552000; includeSubDomains",
      "Transfer-Encoding": "chunked",
      "Vary": "Accept-Encoding, x-va-bild-pur, x-va-adfree, x-va-bildplus, Origin",
      "X-CM-Host": "www.bild.de",
      "X-CM-Uri": "/news/startseite/news/news-16804530.bild.html",
      "X-Content-Type-Options": "nosniff",
      "X-DNS-Prefetch-Control": "off",
      "X-Download-Options": "noopen",
      "X-Permitted-Cross-Domain-Policies": "none",
      "X-Refresh": "s=XXX|h=6|c=|t=20.000|a=3.998|rd=Sat, 28 Feb 2026 22:03:26 GMT|dd=Sat, 28 Feb 2026 22:03:30 GMT",
      "X-UA-Compatible": "IE=Edge",
      "X-XSS-Protection": "0"
    },
    "status": 200,
    "url": "https://www.bild.de/news/startseite/news/news-16804530.bild.html"
  },
  "politik": {
    "date": "2026-03-01T01:27:47.413023",
    "headers": {
      "Access-Control-Expose-Headers": "Server-Timing",
      "Cache-Control": "no-cache, must-revalidate, max-age=10",
      "Connection": "keep-alive, Transfer-Encoding",
      "Content-Security-Policy": "upgrade-insecure-requests",
      "Content-Type": "text/html; charset=utf-8",
      "Date": "Sun, 01 Mar 2026 01:27:47 GMT",
      "ETag": "W/\"4008f-7A0ih8159RKZPMkUMq4hbWU271Y\"",
      "Expect-CT": "max-age=0",
      "Last-Modified": "Sun, 01 Mar 2026 01:13:32 GMT",
      "Server": "Apache",
      "Server-Timing": "traceparent;desc=\"00-cdef9bef0e5468bcf7f2bfec33fa5224-997b2919f5da473c-01\"",
      "Strict-Transport-Security": "max-age=15552000; includeSubDomains",
      "Transfer-Encoding": "chunked",
      "Vary": "Accept-Encoding, x-va-bild-pur, x-va-adfree, x-va-bildplus, Origin",
      "X-CM-Host": "www.bild.de",
      "X-CM-Uri": "/politik/startseite/politik/politik-16804552.bild.html",
      "X-Content-Type-Options": "nosniff",
      "X-DNS-Prefetch-Control": "off",
      "X-Download-Options": "noopen",
      "X-Permitted-Cross-Domain-Policies": "none",
      "X-Refresh": "s=XXX|h=2|c=|t=20.000|a=9.088|rd=Sun, 01 Mar 2026 01:27:38 GMT|dd=Sun, 01 Mar 2026 01:27:47 GMT",
      "X-UA-Compatible": "IE=Edge",
      "X-XSS-Protection": "0"
    },
    "status": 200,
    "url": "https://www.bild.de/politik/startseite/politik/politik-16804552.bild.html"
  },
  "ratgeber": {
    "date": "2026-03-01T01:27:49.812327",
    "headers": {
      "Access-Control-Expose-Headers": "Server-Timing",
      "Cache-Control": "no-cache, must-revalidate, max-age=10",
      "Connection": "keep-alive, Transfer-Encoding",
      "Content-Security-Policy": "upgrade-insecure-requests",
      "Content-Type": "text/html; charset=utf-8",
      "Date": "Sun, 01 Mar 2026 01:27:50 GMT",
      "ETag": "W/\"454a6-M+ZFKPAw1zXNUSd6xbl5jIqpnEs\"",
      "Expect-CT": "max-age=0",
      "Last-Modified": "Sat, 28 Feb 2026 21:09:50 GMT",
      "Server": "Apache",
      "Server-Timing": "traceparent;desc=\"00-473a69381512a85cc9e06ec9cd686469-e4f0fd43dfeef9c8-01\"",
      "Strict-Transport-Security": "max-age=15552000; includeSubDomains",
      "Transfer-Encoding": "chunked",
      "Vary": "Accept-Encoding, x-va-bild-pur, x-va-adfree, x-va-bildplus, Origin",
      "X-CM-Host": "www.bild.de",
      "X-CM-Uri": "/ratgeber/startseite/ratgeber/home-15478376.bild.html",
      "X-Content-Type-Options": "nosniff",
      "X-DNS-Prefetch-Control": "off",
      "X-Download-Options": "noopen",
      "X-Permitted-Cross-Domain-Policies": "none",
      "X-Refresh": "s=XXX|h=1|c=|t=19.550|a=21.167|rd=Sun, 01 Mar 2026 01:27:28 GMT|dd=Sun, 01 Mar 2026 01:27:50 GMT",
      "X-UA-Compatible": "IE=Edge",
      "X-XSS-Protection": "0"
    },
    "status": 200,
    "url": "https://www.bild.de/ratgeber/startseite/ratgeber/home-15478376.bild.html"
  },
  "ratgeber2": {
    "date": "2026-03-01T01:27:56.524590",
    "headers": {
      "Access-Control-Expose-Headers": "Server-Timing",
      "Cache-Control": "no-cache, must-revalidate, max-age=10",
      "Connection": "keep-alive, Transfer-Encoding",
      "Content-Security-Policy": "upgrade-insecure-requests",
      "Content-Type": "text/html; charset=utf-8",
      "Date": "Sun, 01 Mar 2026 01:27:56 GMT",
      "ETag": "W/\"3da60-+94353YYGWCNf5U9lEtfE89PdcQ\"",
      "Expect-CT": "max-age=0",
      "Last-Modified": "Sat, 28 Feb 2026 21:09:50 GMT",
      "Server": "Apache",
      "Server-Timing": "traceparent;desc=\"00-179ee28da8b9940f5f7b1058c7a13d43-1a94d00a5584d350-01\"",
      "Strict-Transport-Security": "max-age=15552000; includeSubDomains",
      "Transfer-Encoding": "chunked",
      "Vary": "Accept-Encoding, x-va-bild-pur, x-va-adfree, x-va-bildplus, Origin",
      "X-CM-Host": "m.bild.de",
      "X-CM-Uri": "/ratgeber/startseite/ratgeber/home-15478376.bildMobile.html",
      "X-Content-Type-Options": "nosniff",
      "X-DNS-Prefetch-Control": "off",
      "X-Download-Options": "noopen",
      "X-Permitted-Cross-Domain-Policies": "none",
      "X-Refresh": "s=XXX|h=0|c=|t=19.943|a=0.000|rd=Sun, 01 Mar 2026 01:27:56 GMT|dd=Sun, 01 Mar 2026 01:27:56 GMT",
      "X-UA-Compatible": "IE=Edge",
      "X-XSS-Protection": "0"
    },
    "status": 200,
    "url": "https://m.bild.de/ratgeber/startseite/ratgeber/home-15478376.bildMobile.html"
  },
  "regio": {
    "date": "2026-03-01T01:27:48.067281",
    "headers": {
      "Access-Control-Expose-Headers": "Server-Timing",
      "Cache-Control": "no-cache, must-revalidate, max-age=10",
      "Connection": "keep-alive, Transfer-Encoding",
      "Content-Security-Policy": "upgrade-insecure-requests",
      "Content-Type": "text/html; charset=utf-8",
      "Date": "Sun, 01 Mar 2026 01:27:48 GMT",
      "ETag": "W/\"5f87a-2L0URYUGTrlrS6J81jnNYIxsTts\"",
      "Expect-CT": "max-age=0",
      "Last-Modified": "Sat, 28 Feb 2026 23:28:51 GMT",
      "Server": "Apache",
      "Server-Timing": "traceparent;desc=\"00-58be09e8ce1b986476ec40eb8d445bea-4d2b297892cb4d70-01\"",
      "Strict-Transport-Security": "max-age=15552000; includeSubDomains",
      "Transfer-Encoding": "chunked",
      "Vary": "Accept-Encoding, x-va-bild-pur, x-va-adfree, x-va-bildplus, Origin",
      "X-CM-Host": "www.bild.de",
      "X-CM-Uri": "/regional/startseite/regional/regio-15799990.bild.html",
      "X-Content-Type-Options": "nosniff",
      "X-DNS-Prefetch-Control": "off",
      "X-Download-Options": "noopen",
      "X-Permitted-Cross-Domain-Policies": "none",
      "X-Refresh": "s=XXX|h=1|c=|t=19.018|a=7.172|rd=Sun, 01 Mar 2026 01:27:40 GMT|dd=Sun, 01 Mar 2026 01:27:48 GMT",
      "X-UA-Compatible": "IE=Edge",
      "X-XSS-Protection": "0"
    },
    "status": 200,
    "url": "https://www.bild.de/regional/startseite/regional/regio-15799990.bild.html"
  },
  "reise": {
    "date": "2026-03-01T01:27:55.087082",
    "headers": {
      "Access-Control-Expose-Headers": "Server-Timing",
      "Cache-Control": "no-cache, must-revalidate, max-age=10",
      "Connection": "keep-alive, Transfer-Encoding",
      "Content-Security-Policy": "upgrade-insecure-requests",
      "Content-Type": "text/html; charset=utf-8",
      "Date": "Sun, 01 Mar 2026 01:27:55 GMT",
      "ETag": "W/\"34867-s05NmArsOxrgBq0ROzF0fT1RM5U\"",
      "Expect-CT": "max-age=0",
      "Last-Modified": "Sat, 28 Feb 2026 13:54:34 GMT",
      "Server": "Apache",
      "Server-Timing": "traceparent;desc=\"00-c6edd30592a205e9cc964e14ca250290-c53c3628530edc9d-01\"",
      "Strict-Transport-Security": "max-age=15552000; includeSubDomains",
      "Transfer-Encoding": "chunked",
      "Vary": "Accept-Encoding, x-va-bild-pur, x-va-adfree, x-va-bildplus, Origin",
      "X-CM-Host": "www.bild.de",
      "X-CM-Uri": "/reise/startseite/aktivurlaub/reise-15478744.bild.html",
      "X-Content-Type-Options": "nosniff",
      "X-DNS-Prefetch-Control": "off",
      "X-Download-Options": "noopen",
      "X-Permitted-Cross-Domain-Policies": "none",
      "X-Refresh": "s=XXX|h=0|c=|t=19.891|a=0.000|rd=Sun, 01 Mar 2026 01:27:55 GMT|dd=Sun, 01 Mar 2026 01:27:55 GMT",
      "X-UA-Compatible": "IE=Edge",
      "X-XSS-Protection": "0"
    },
    "status": 200,
    "url": "https://www.bild.de/reise/startseite/aktivurlaub/reise-15478744.bild.html"
  },
  "reise2": {
    "date": "2026-03-01T01:27:56.889784",
    "headers": {
      "Access-Control-Expose-Headers": "Server-Timing",
      "Cache-Control": "no-cache, must-revalidate, max-age=10",
      "Connection": "keep-alive, Transfer-Encoding",
      "Content-Security-Policy": "upgrade-insecure-requests",
      "Content-Type": "text/html; charset=utf-8",
      "Date": "Sun, 01 Mar 2026 01:27:57 GMT",
      "ETag": "W/\"2bd27-e6XgqrZHIJVqAO14IsZYU4oVxu8\"",
      "Expect-CT": "max-age=0",
      "Last-Modified": "Sat, 28 Feb 2026 13:54:34 GMT",
      "Server": "Apache",
      "Server-Timing": "traceparent;desc=\"00-3334e0fbab195aa769f96f1153d883ec-03ba19a4d793991d-01\"",
      "Strict-Transport-Security": "max-age=15552000; includeSubDomains",
      "Transfer-Encoding": "chunked",
      "Vary": "Accept-Encoding, x-va-bild-pur, x-va-adfree, x-va-bildplus, Origin",
      "X-CM-Host": "m.bild.de",
      "X-CM-Uri": "/reise/startseite/aktivurlaub/reise-15478744.bildMobile.html",
      "X-Content-Type-Options": "nosniff",
      "X-DNS-Prefetch-Control": "off",
      "X-Download-Options": "noopen",
      "X-Permitted-Cross-Domain-Policies": "none",
      "X-Refresh": "s=XXX|h=0|c=|t=19.901|a=0.000|rd=Sun, 01 Mar 2026 01:27:57 GMT|dd=Sun, 01 Mar 2026 01:27:57 GMT",
      "X-UA-Compatible": "IE=Edge",
      "X-XSS-Protection": "0"
    },
    "status": 200,
    "url": "https://m.bild.de/reise/startseite/aktivurlaub/reise-15478744.bildMobile.html"
  },
  "sport": {
    "date": "2026-03-01T01:27:49.063978",
    "headers": {
      "Access-Control-Expose-Headers": "Server-Timing",
      "Cache-Control": "no-cache, must-revalidate, max-age=10",
      "Connection": "keep-alive, Transfer-Encoding",
      "Content-Security-Policy": "upgrade-insecure-requests",
      "Content-Type": "text/html; charset=utf-8",
      "Date": "Sun, 01 Mar 2026 01:27:49 GMT",
      "ETag": "W/\"5a700-MeP+siWZi/PCQMwbzpy+80hSVXQ\"",
      "Expect-CT": "max-age=0",
      "Last-Modified": "Sun, 01 Mar 2026 01:26:52 GMT",
      "Server": "Apache",
      "Server-Timing": "traceparent;desc=\"00-ee8046df9d30a5a63e91fa885aba00bb-709eb2255aaed394-01\"",
      "Strict-Transport-Security": "max-age=15552000; includeSubDomains",
      "Transfer-Encoding": "chunked",
      "Vary": "Accept-Encoding, x-va-bild-pur, x-va-adfree, x-va-bildplus, Origin",
      "X-CM-Host": "www.bild.de",
      "X-CM-Uri": "/sport/startseite/sport/sport-home-15479124.bild.html",
      "X-Content-Type-Options": "nosniff",
      "X-DNS-Prefetch-Control": "off",
      "X-Download-Options": "noopen",
      "X-Permitted-Cross-Domain-Policies": "none",
      "X-Refresh": "s=XXX|h=2|c=|t=20.000|a=6.171|rd=Sun, 01 Mar 2026 01:27:43 GMT|dd=Sun, 01 Mar 2026 01:27:49 GMT",
      "X-UA-Compatible": "IE=Edge",
      "X-XSS-Protection": "0"
    },
    "status": 200,
    "url": "https://www.bild.de/sport/startseite/sport/sport-home-15479124.bild.html"
  },
  "stars": {
    "date": "2026-03-01T01:27:53.738651",
    "headers": {
      "Access-Control-Expose-Headers": "Server-Timing",
      "Cache-Control": "no-cache, must-revalidate, max-age=10",
      "Connection": "keep-alive, Transfer-Encoding",
      "Content-Security-Policy": "upgrade-insecure-requests",
      "Content-Type": "text/html; charset=utf-8",
      "Date": "Sun, 01 Mar 2026 01:27:54 GMT",
      "ETag": "W/\"31039-aVS7D8X7vzjHPNgjdWAEz00+4Vk\"",
      "Expect-CT": "max-age=0",
      "Last-Modified": "Sat, 28 Feb 2026 18:04:11 GMT",
      "Server": "Apache",
      "Server-Timing": "traceparent;desc=\"00-67bed550d3a1db85f16b0e0b44ba177f-a46bd7b5075654b3-01\"",
      "Strict-Transport-Security": "max-age=15552000; includeSubDomains",
      "Transfer-Encoding": "chunked",
      "Vary": "Accept-Encoding, x-va-bild-pur, x-va-adfree, x-va-bildplus, Origin",
      "X-CM-Host": "www.bild.de",
      "X-CM-Uri": "/unterhaltung/leute/leute/home-15684852.bild.html",
      "X-Content-Type-Options": "nosniff",
      "X-DNS-Prefetch-Control": "off",
      "X-Download-Options": "noopen",
      "X-Permitted-Cross-Domain-Policies": "none",
      "X-Refresh": "s=XXX|h=1|c=|t=19.576|a=16.179|rd=Sun, 01 Mar 2026 01:27:37 GMT|dd=Sun, 01 Mar 2026 01:27:54 GMT",
      "X-UA-Compatible": "IE=Edge",
      "X-XSS-Protection": "0"
    },
    "status": 200,
    "url": "https://www.bild.de/unterhaltung/leute/leute/home-15684852.bild.html"
  },
  "tv": {
    "date": "2026-03-01T01:27:54.475040",
    "headers": {
      "Access-Control-Expose-Headers": "Server-Timing",
      "Cache-Control": "no-cache, must-revalidate, max-age=10",
      "Connection": "keep-alive, Transfer-Encoding",
      "Content-Security-Policy": "upgrade-insecure-requests",
      "Content-Type": "text/html; charset=utf-8",
      "Date": "Sun, 01 Mar 2026 01:27:54 GMT",
      "ETag": "W/\"2e89c-EpRV5LmWPD/Mkv6Xusqf1rCcC1U\"",
      "Expect-CT": "max-age=0",
      "Last-Modified": "Sat, 28 Feb 2026 23:04:39 GMT",
      "Server": "Apache",
      "Server-Timing": "traceparent;desc=\"00-1e0f296e033d9665cba3257e103ecc93-4b244d918a0cc65d-01\"",
      "Strict-Transport-Security": "max-age=15552000; includeSubDomains",
      "Transfer-Encoding": "chunked",
      "Vary": "Accept-Encoding, x-va-bild-pur, x-va-adfree, x-va-bildplus, Origin",
      "X-CM-Host": "www.bild.de",
      "X-CM-Uri": "/unterhaltung/tv/tv/tv-15479870.bild.html",
      "X-Content-Type-Options": "nosniff",
      "X-DNS-Prefetch-Control": "off",
      "X-Download-Options": "noopen",
      "X-Permitted-Cross-Domain-Policies": "none",
      "X-Refresh": "s=XXX|h=2|c=|t=20.000|a=14.079|rd=Sun, 01 Mar 2026 01:27:40 GMT|dd=Sun, 01 Mar 2026 01:27:54 GMT",
      "X-UA-Compatible": "IE=Edge",
      "X-XSS-Protection": "0"
    },
    "status": 200,
    "url": "https://www.bild.de/unterhaltung/tv/tv/tv-15479870.bild.html"
  },
  "unterhaltung": {
    "date": "2026-03-01T01:27:48.576269",
    "headers": {
      "Access-Control-Expose-Headers": "Server-Timing",
      "Cache-Control": "no-cache, must-revalidate, max-age=10",
      "Connection": "keep-alive, Transfer-Encoding",
      "Content-Security-Policy": "upgrade-insecure-requests",
      "Content-Type": "text/html; charset=utf-8",
      "Date": "Sun, 01 Mar 2026 01:27:48 GMT",
      "ETag": "W/\"4dc60-uKbr9s08fGpGJC1tOKYwKCwzoGE\"",
      "Expect-CT": "max-age=0",
      "Last-Modified": "Sat, 28 Feb 2026 23:01:51 GMT",
      "Server": "Apache",
      "Server-Timing": "traceparent;desc=\"00-bd24c357f310eece2f7fc1d36ff6de33-09049b1284f13e99-01\"",
      "Strict-Transport-Security": "max-age=15552000; includeSubDomains",
      "Transfer-Encoding": "chunked",
      "Vary": "Accept-Encoding, x-va-bild-pur, x-va-adfree, x-va-bildplus, Origin",
      "X-CM-Host": "www.bild.de",
      "X-CM-Uri": "/unterhaltung/startseite/unterhaltung/show-16804710.bild.html",
      "X-Content-Type-Options": "nosniff",
      "X-DNS-Prefetch-Control": "off",
      "X-Download-Options": "noopen",
      "X-Permitted-Cross-Domain-Policies": "none",
      "X-Refresh": "s=XXX|h=3|c=|t=20.000|a=18.182|rd=Sun, 01 Mar 2026 01:27:30 GMT|dd=Sun, 01 Mar 2026 01:27:48 GMT",
      "X-UA-Compatible": "IE=Edge",
      "X-XSS-Protection": "0"
    },
    "status": 200,
    "url": "https://www.bild.de/unterhaltung/startseite/unterhaltung/show-16804710.bild.html"
  }
}