{
  "aktuell.html": {
    "date": "2022-11-01T02:36:50.414554",
    "headers": {
      "Connection": "keep-alive",
      "Content-Type": "text/html; charset=UTF-8",
      "Date": "Tue, 01 Nov 2022 02:36:50 GMT",
      "Link": "<https://www.compact-online.de/?p=191092>; rel=shortlink",
      "Referrer-Policy": "no-referrer-when-downgrade",
      "Server": "nginx",
      "Transfer-Encoding": "chunked",
      "Vary": "Accept-Encoding, Accept-Encoding",
      "X-Cache-Status": "STALE",
      "X-Powered-By": "PHP/8.0.24, PleskLin",
      "dlm-no-waypoints": "true"
    },
    "status": 200,
    "url": "https://www.compact-online.de/compact-aktuell/"
  },
  "datenschutz.html": {
    "date": "2022-11-01T02:36:53.258632",
    "headers": {
      "Accept-Ranges": "bytes",
      "Connection": "keep-alive",
      "Content-Length": "97820",
      "Content-Type": "text/html; charset=UTF-8",
      "Date": "Tue, 01 Nov 2022 02:36:53 GMT",
      "ETag": "\"17e1c-5ec5479b29de9\"",
      "Referrer-Policy": "no-referrer-when-downgrade",
      "Server": "nginx",
      "Vary": "Accept-Encoding, Accept-Encoding",
      "X-Cache-Status": "MISS",
      "X-Powered-By": "PleskLin"
    },
    "status": 200,
    "url": "https://www.compact-online.de/rechtliches/datenschutz/"
  },
  "impressum.html": {
    "date": "2022-11-01T02:36:53.150033",
    "headers": {
      "Accept-Ranges": "bytes",
      "Connection": "keep-alive",
      "Content-Length": "72187",
      "Content-Type": "text/html; charset=UTF-8",
      "Date": "Tue, 01 Nov 2022 02:36:53 GMT",
      "ETag": "\"119fb-5ec546343013f\"",
      "Referrer-Policy": "no-referrer-when-downgrade",
      "Server": "nginx",
      "Vary": "Accept-Encoding, Accept-Encoding",
      "X-Cache-Status": "MISS",
      "X-Powered-By": "PleskLin"
    },
    "status": 200,
    "url": "https://www.compact-online.de/rechtliches/impressum/"
  },
  "index.html": {
    "date": "2022-11-01T02:36:49.432590",
    "headers": {
      "Accept-Ranges": "bytes",
      "Connection": "keep-alive",
      "Content-Length": "343393",
      "Content-Type": "text/html; charset=UTF-8",
      "Date": "Tue, 01 Nov 2022 02:36:49 GMT",
      "ETag": "\"53d61-5ec5ab81bced1\"",
      "Referrer-Policy": "no-referrer-when-downgrade",
      "Server": "nginx",
      "Vary": "Accept-Encoding, Accept-Encoding",
      "X-Cache-Status": "STALE",
      "X-Powered-By": "PleskLin"
    },
    "status": 200,
    "url": "https://www.compact-online.de/"
  },
  "plus.html": {
    "date": "2022-11-01T02:36:50.313806",
    "headers": {
      "Accept-Ranges": "bytes",
      "Connection": "keep-alive",
      "Content-Length": "184492",
      "Content-Type": "text/html; charset=UTF-8",
      "Date": "Tue, 01 Nov 2022 02:36:50 GMT",
      "ETag": "\"2d0ac-5ec546db2ec56\"",
      "Referrer-Policy": "no-referrer-when-downgrade",
      "Server": "nginx",
      "Vary": "Accept-Encoding, Accept-Encoding",
      "X-Cache-Status": "STALE",
      "X-Powered-By": "PleskLin"
    },
    "status": 200,
    "url": "https://www.compact-online.de/plus/"
  },
  "tv.html": {
    "date": "2022-11-01T02:36:50.514709",
    "headers": {
      "Accept-Ranges": "bytes",
      "Connection": "keep-alive",
      "Content-Length": "184172",
      "Content-Type": "text/html; charset=UTF-8",
      "Date": "Tue, 01 Nov 2022 02:36:52 GMT",
      "ETag": "\"2cf6c-5ec544abc55b7\"",
      "Referrer-Policy": "no-referrer-when-downgrade",
      "Server": "nginx",
      "Vary": "Accept-Encoding, Accept-Encoding",
      "X-Cache-Status": "STALE",
      "X-Powered-By": "PleskLin"
    },
    "status": 200,
    "url": "https://tv.compact-online.de/"
  }
}