{
  "allgemeines.html": {
    "date": "2026-02-01T01:29:39.394719",
    "headers": {
      "CF-RAY": "9c6dadd6bd66d567-LAX",
      "Cache-Control": "private, max-age=0, no-store, no-cache, must-revalidate, post-check=0, pre-check=0",
      "Connection": "close",
      "Content-Type": "text/html; charset=UTF-8",
      "Date": "Sun, 01 Feb 2026 01:29:39 GMT",
      "Expires": "Thu, 01 Jan 1970 00:00:01 GMT",
      "NEL": "{\"success_fraction\":0,\"report_to\":\"cf-nel\",\"max_age\":604800}",
      "Report-To": "{\"endpoints\":[{\"url\":\"https:\\/\\/a.nel.cloudflare.com\\/report\\/v4?s=MUm73a8QEG3jJYnWxNEUSPu1K3k2FvyVNzKhEGdfDxPmJeJfsl7Tv%2BWPO8YX6gYV6zT25x2XCXtKvL7Cpwl4AmR0MT5triAnKwhzFXUqTcRg0YXK7xIoROoAkeKb3dAQRL63hBhwLz0rpA%3D%3D\"}],\"group\":\"cf-nel\",\"max_age\":604800}",
      "Server": "cloudflare",
      "Transfer-Encoding": "chunked",
      "Vary": "Accept-Encoding",
      "accept-ch": "Sec-CH-UA-Bitness, Sec-CH-UA-Arch, Sec-CH-UA-Full-Version, Sec-CH-UA-Mobile, Sec-CH-UA-Model, Sec-CH-UA-Platform-Version, Sec-CH-UA-Full-Version-List, Sec-CH-UA-Platform, Sec-CH-UA, UA-Bitness, UA-Arch, UA-Full-Version, UA-Mobile, UA-Model, UA-Platform-Version, UA-Platform, UA",
      "alt-svc": "h3=\":443\"; ma=86400",
      "cf-mitigated": "challenge",
      "critical-ch": "Sec-CH-UA-Bitness, Sec-CH-UA-Arch, Sec-CH-UA-Full-Version, Sec-CH-UA-Mobile, Sec-CH-UA-Model, Sec-CH-UA-Platform-Version, Sec-CH-UA-Full-Version-List, Sec-CH-UA-Platform, Sec-CH-UA, UA-Bitness, UA-Arch, UA-Full-Version, UA-Mobile, UA-Model, UA-Platform-Version, UA-Platform, UA",
      "cross-origin-embedder-policy": "require-corp",
      "cross-origin-opener-policy": "same-origin",
      "cross-origin-resource-policy": "same-origin",
      "origin-agent-cluster": "?1",
      "permissions-policy": "accelerometer=(),browsing-topics=(),camera=(),clipboard-read=(),clipboard-write=(),geolocation=(),gyroscope=(),hid=(),interest-cohort=(),magnetometer=(),microphone=(),payment=(),publickey-credentials-get=(),screen-wake-lock=(),serial=(),sync-xhr=(),usb=()",
      "referrer-policy": "same-origin",
      "server-timing": "chlray;desc=\"9c6dadd6bd66d567\", cfL4;desc=\"?proto=TCP&rtt=9056&min_rtt=8832&rtt_var=2683&sent=4&recv=7&lost=0&retrans=0&sent_bytes=2854&recv_bytes=774&delivery_rate=323150&cwnd=251&unsent_bytes=0&cid=fa9e329abec7669f&ts=34&x=0\"",
      "x-content-type-options": "nosniff",
      "x-frame-options": "SAMEORIGIN"
    },
    "status": 403,
    "url": "https://www.spiegeldaily.de/category/allgemeines/"
  },
  "datenschutz.html": {
    "date": "2026-02-01T01:29:39.718279",
    "headers": {
      "CF-RAY": "9c6dadd87c0536e7-LAX",
      "Cache-Control": "private, max-age=0, no-store, no-cache, must-revalidate, post-check=0, pre-check=0",
      "Connection": "close",
      "Content-Type": "text/html; charset=UTF-8",
      "Date": "Sun, 01 Feb 2026 01:29:39 GMT",
      "Expires": "Thu, 01 Jan 1970 00:00:01 GMT",
      "NEL": "{\"success_fraction\":0,\"report_to\":\"cf-nel\",\"max_age\":604800}",
      "Report-To": "{\"endpoints\":[{\"url\":\"https:\\/\\/a.nel.cloudflare.com\\/report\\/v4?s=6ljy%2FNIakDhsboL0VrnPiNPPqQOAT7JbgrmwKCjrKv%2BTixyiANrrnDWtuGjmscStjY1OvApacqPnjMTZ1RLZpuy7%2F5XPXwPAwZrwX57GTDHAI0iVEkFA04KR0TjligcIRd0KaDw872TE6w%3D%3D\"}],\"group\":\"cf-nel\",\"max_age\":604800}",
      "Server": "cloudflare",
      "Transfer-Encoding": "chunked",
      "Vary": "Accept-Encoding",
      "accept-ch": "Sec-CH-UA-Bitness, Sec-CH-UA-Arch, Sec-CH-UA-Full-Version, Sec-CH-UA-Mobile, Sec-CH-UA-Model, Sec-CH-UA-Platform-Version, Sec-CH-UA-Full-Version-List, Sec-CH-UA-Platform, Sec-CH-UA, UA-Bitness, UA-Arch, UA-Full-Version, UA-Mobile, UA-Model, UA-Platform-Version, UA-Platform, UA",
      "alt-svc": "h3=\":443\"; ma=86400",
      "cf-mitigated": "challenge",
      "critical-ch": "Sec-CH-UA-Bitness, Sec-CH-UA-Arch, Sec-CH-UA-Full-Version, Sec-CH-UA-Mobile, Sec-CH-UA-Model, Sec-CH-UA-Platform-Version, Sec-CH-UA-Full-Version-List, Sec-CH-UA-Platform, Sec-CH-UA, UA-Bitness, UA-Arch, UA-Full-Version, UA-Mobile, UA-Model, UA-Platform-Version, UA-Platform, UA",
      "cross-origin-embedder-policy": "require-corp",
      "cross-origin-opener-policy": "same-origin",
      "cross-origin-resource-policy": "same-origin",
      "origin-agent-cluster": "?1",
      "permissions-policy": "accelerometer=(),browsing-topics=(),camera=(),clipboard-read=(),clipboard-write=(),geolocation=(),gyroscope=(),hid=(),interest-cohort=(),magnetometer=(),microphone=(),payment=(),publickey-credentials-get=(),screen-wake-lock=(),serial=(),sync-xhr=(),usb=()",
      "referrer-policy": "same-origin",
      "server-timing": "chlray;desc=\"9c6dadd87c0536e7\", cfL4;desc=\"?proto=TCP&rtt=8385&min_rtt=8188&rtt_var=3211&sent=4&recv=6&lost=0&retrans=0&sent_bytes=2855&recv_bytes=774&delivery_rate=348803&cwnd=248&unsent_bytes=0&cid=c1483b3c76c4adba&ts=48&x=0\"",
      "x-content-type-options": "nosniff",
      "x-frame-options": "SAMEORIGIN"
    },
    "status": 403,
    "url": "https://www.spiegeldaily.de/datenschutzerklaerung/"
  },
  "freizeit.html": {
    "date": "2026-02-01T01:29:38.747206",
    "headers": {
      "CF-RAY": "9c6dadd26eb41e1d-LAX",
      "Cache-Control": "private, max-age=0, no-store, no-cache, must-revalidate, post-check=0, pre-check=0",
      "Connection": "close",
      "Content-Type": "text/html; charset=UTF-8",
      "Date": "Sun, 01 Feb 2026 01:29:38 GMT",
      "Expires": "Thu, 01 Jan 1970 00:00:01 GMT",
      "NEL": "{\"success_fraction\":0,\"report_to\":\"cf-nel\",\"max_age\":604800}",
      "Report-To": "{\"endpoints\":[{\"url\":\"https:\\/\\/a.nel.cloudflare.com\\/report\\/v4?s=peB81gqR%2B1quFNEeAO7SpHbWF3lx4baOQoYiqCP00MUorYhAFsXJkvYzoijAwZ%2BuMto8XUwfbCnZtUsE%2F6NM5HeSnHMjUwsbdbMt3OhF0yvbjIO%2FK0Ci4lhbj8gb%2FFVF564lPHuDOY0adQ%3D%3D\"}],\"group\":\"cf-nel\",\"max_age\":604800}",
      "Server": "cloudflare",
      "Transfer-Encoding": "chunked",
      "Vary": "Accept-Encoding",
      "accept-ch": "Sec-CH-UA-Bitness, Sec-CH-UA-Arch, Sec-CH-UA-Full-Version, Sec-CH-UA-Mobile, Sec-CH-UA-Model, Sec-CH-UA-Platform-Version, Sec-CH-UA-Full-Version-List, Sec-CH-UA-Platform, Sec-CH-UA, UA-Bitness, UA-Arch, UA-Full-Version, UA-Mobile, UA-Model, UA-Platform-Version, UA-Platform, UA",
      "alt-svc": "h3=\":443\"; ma=86400",
      "cf-mitigated": "challenge",
      "critical-ch": "Sec-CH-UA-Bitness, Sec-CH-UA-Arch, Sec-CH-UA-Full-Version, Sec-CH-UA-Mobile, Sec-CH-UA-Model, Sec-CH-UA-Platform-Version, Sec-CH-UA-Full-Version-List, Sec-CH-UA-Platform, Sec-CH-UA, UA-Bitness, UA-Arch, UA-Full-Version, UA-Mobile, UA-Model, UA-Platform-Version, UA-Platform, UA",
      "cross-origin-embedder-policy": "require-corp",
      "cross-origin-opener-policy": "same-origin",
      "cross-origin-resource-policy": "same-origin",
      "origin-agent-cluster": "?1",
      "permissions-policy": "accelerometer=(),browsing-topics=(),camera=(),clipboard-read=(),clipboard-write=(),geolocation=(),gyroscope=(),hid=(),interest-cohort=(),magnetometer=(),microphone=(),payment=(),publickey-credentials-get=(),screen-wake-lock=(),serial=(),sync-xhr=(),usb=()",
      "referrer-policy": "same-origin",
      "server-timing": "chlray;desc=\"9c6dadd26eb41e1d\", cfL4;desc=\"?proto=TCP&rtt=8507&min_rtt=8335&rtt_var=3248&sent=4&recv=6&lost=0&retrans=0&sent_bytes=2855&recv_bytes=774&delivery_rate=342651&cwnd=251&unsent_bytes=0&cid=550d1b7ad69ffc68&ts=29&x=0\"",
      "x-content-type-options": "nosniff",
      "x-frame-options": "SAMEORIGIN"
    },
    "status": 403,
    "url": "https://www.spiegeldaily.de/category/freizeit/"
  },
  "index.html": {
    "date": "2026-02-01T01:29:37.674469",
    "headers": {
      "CF-RAY": "9c6dadd09c4ecbaa-LAX",
      "Cache-Control": "private, max-age=0, no-store, no-cache, must-revalidate, post-check=0, pre-check=0",
      "Connection": "close",
      "Content-Type": "text/html; charset=UTF-8",
      "Date": "Sun, 01 Feb 2026 01:29:38 GMT",
      "Expires": "Thu, 01 Jan 1970 00:00:01 GMT",
      "NEL": "{\"success_fraction\":0,\"report_to\":\"cf-nel\",\"max_age\":604800}",
      "Report-To": "{\"endpoints\":[{\"url\":\"https:\\/\\/a.nel.cloudflare.com\\/report\\/v4?s=fOsfHZbR1rCzVz7%2Bmm9gD6FVNDOdyEGX7nmpxnLwdA9g0bxX0FWLcW%2Fom8dU4PGU%2Ft2NeFN8v5vavgzQw4B2n3TYJFleXZIwUYF3sC3lDUfJHmi4%2Fe22wQtU4JCMeOD2Z1HMceP6r054gg%3D%3D\"}],\"group\":\"cf-nel\",\"max_age\":604800}",
      "Server": "cloudflare",
      "Transfer-Encoding": "chunked",
      "Vary": "Accept-Encoding",
      "accept-ch": "Sec-CH-UA-Bitness, Sec-CH-UA-Arch, Sec-CH-UA-Full-Version, Sec-CH-UA-Mobile, Sec-CH-UA-Model, Sec-CH-UA-Platform-Version, Sec-CH-UA-Full-Version-List, Sec-CH-UA-Platform, Sec-CH-UA, UA-Bitness, UA-Arch, UA-Full-Version, UA-Mobile, UA-Model, UA-Platform-Version, UA-Platform, UA",
      "alt-svc": "h3=\":443\"; ma=86400",
      "cf-mitigated": "challenge",
      "critical-ch": "Sec-CH-UA-Bitness, Sec-CH-UA-Arch, Sec-CH-UA-Full-Version, Sec-CH-UA-Mobile, Sec-CH-UA-Model, Sec-CH-UA-Platform-Version, Sec-CH-UA-Full-Version-List, Sec-CH-UA-Platform, Sec-CH-UA, UA-Bitness, UA-Arch, UA-Full-Version, UA-Mobile, UA-Model, UA-Platform-Version, UA-Platform, UA",
      "cross-origin-embedder-policy": "require-corp",
      "cross-origin-opener-policy": "same-origin",
      "cross-origin-resource-policy": "same-origin",
      "origin-agent-cluster": "?1",
      "permissions-policy": "accelerometer=(),browsing-topics=(),camera=(),clipboard-read=(),clipboard-write=(),geolocation=(),gyroscope=(),hid=(),interest-cohort=(),magnetometer=(),microphone=(),payment=(),publickey-credentials-get=(),screen-wake-lock=(),serial=(),sync-xhr=(),usb=()",
      "referrer-policy": "same-origin",
      "server-timing": "chlray;desc=\"9c6dadd09c4ecbaa\", cfL4;desc=\"?proto=TCP&rtt=8414&min_rtt=8270&rtt_var=3204&sent=4&recv=6&lost=0&retrans=0&sent_bytes=2855&recv_bytes=774&delivery_rate=345344&cwnd=251&unsent_bytes=0&cid=98475eb2a74f522a&ts=37&x=0\"",
      "x-content-type-options": "nosniff",
      "x-frame-options": "SAMEORIGIN"
    },
    "status": 403,
    "url": "https://www.spiegeldaily.de/"
  },
  "leben.html": {
    "date": "2026-02-01T01:29:38.965399",
    "headers": {
      "CF-RAY": "9c6dadd3cb555b5f-LAX",
      "Cache-Control": "private, max-age=0, no-store, no-cache, must-revalidate, post-check=0, pre-check=0",
      "Connection": "close",
      "Content-Type": "text/html; charset=UTF-8",
      "Date": "Sun, 01 Feb 2026 01:29:39 GMT",
      "Expires": "Thu, 01 Jan 1970 00:00:01 GMT",
      "NEL": "{\"success_fraction\":0,\"report_to\":\"cf-nel\",\"max_age\":604800}",
      "Report-To": "{\"endpoints\":[{\"url\":\"https:\\/\\/a.nel.cloudflare.com\\/report\\/v4?s=ENx0K3WCkPJj1vqrvXZNgLAGr68lxW5xiM0eT54knnz5RikxuYCKaWUjISNimqXKVWBREVnOYpJn0UEtA3cEff1A73DIU5G0d2XUjCsu4KhOttMDXDtaHwu5iIgX6KDOxjFl78NYYbQCoA%3D%3D\"}],\"group\":\"cf-nel\",\"max_age\":604800}",
      "Server": "cloudflare",
      "Transfer-Encoding": "chunked",
      "Vary": "Accept-Encoding",
      "accept-ch": "Sec-CH-UA-Bitness, Sec-CH-UA-Arch, Sec-CH-UA-Full-Version, Sec-CH-UA-Mobile, Sec-CH-UA-Model, Sec-CH-UA-Platform-Version, Sec-CH-UA-Full-Version-List, Sec-CH-UA-Platform, Sec-CH-UA, UA-Bitness, UA-Arch, UA-Full-Version, UA-Mobile, UA-Model, UA-Platform-Version, UA-Platform, UA",
      "alt-svc": "h3=\":443\"; ma=86400",
      "cf-mitigated": "challenge",
      "critical-ch": "Sec-CH-UA-Bitness, Sec-CH-UA-Arch, Sec-CH-UA-Full-Version, Sec-CH-UA-Mobile, Sec-CH-UA-Model, Sec-CH-UA-Platform-Version, Sec-CH-UA-Full-Version-List, Sec-CH-UA-Platform, Sec-CH-UA, UA-Bitness, UA-Arch, UA-Full-Version, UA-Mobile, UA-Model, UA-Platform-Version, UA-Platform, UA",
      "cross-origin-embedder-policy": "require-corp",
      "cross-origin-opener-policy": "same-origin",
      "cross-origin-resource-policy": "same-origin",
      "origin-agent-cluster": "?1",
      "permissions-policy": "accelerometer=(),browsing-topics=(),camera=(),clipboard-read=(),clipboard-write=(),geolocation=(),gyroscope=(),hid=(),interest-cohort=(),magnetometer=(),microphone=(),payment=(),publickey-credentials-get=(),screen-wake-lock=(),serial=(),sync-xhr=(),usb=()",
      "referrer-policy": "same-origin",
      "server-timing": "chlray;desc=\"9c6dadd3cb555b5f\", cfL4;desc=\"?proto=TCP&rtt=8549&min_rtt=8325&rtt_var=3282&sent=4&recv=6&lost=0&retrans=0&sent_bytes=2855&recv_bytes=774&delivery_rate=343063&cwnd=251&unsent_bytes=0&cid=7c5b56d96b0016d8&ts=28&x=0\"",
      "x-content-type-options": "nosniff",
      "x-frame-options": "SAMEORIGIN"
    },
    "status": 403,
    "url": "https://www.spiegeldaily.de/category/leben/"
  },
  "lebensstil.html": {
    "date": "2026-02-01T01:29:39.181900",
    "headers": {
      "CF-RAY": "9c6dadd51ac655da-LAX",
      "Cache-Control": "private, max-age=0, no-store, no-cache, must-revalidate, post-check=0, pre-check=0",
      "Connection": "close",
      "Content-Type": "text/html; charset=UTF-8",
      "Date": "Sun, 01 Feb 2026 01:29:39 GMT",
      "Expires": "Thu, 01 Jan 1970 00:00:01 GMT",
      "NEL": "{\"success_fraction\":0,\"report_to\":\"cf-nel\",\"max_age\":604800}",
      "Report-To": "{\"endpoints\":[{\"url\":\"https:\\/\\/a.nel.cloudflare.com\\/report\\/v4?s=oQM0YI%2BMI8%2BURghYzAbetEMuMNEj26oPwJDI5v%2BcPgEYiPpBhTY9XrvN09jFQK%2F3OUrEidJyV%2FF9OzzjNMFuhnl481amIF5t6M170DfFG%2Bw%2FxjHjzRwAn8jpCPmcrl3AHzFtHQH4I5QTJg%3D%3D\"}],\"group\":\"cf-nel\",\"max_age\":604800}",
      "Server": "cloudflare",
      "Transfer-Encoding": "chunked",
      "Vary": "Accept-Encoding",
      "accept-ch": "Sec-CH-UA-Bitness, Sec-CH-UA-Arch, Sec-CH-UA-Full-Version, Sec-CH-UA-Mobile, Sec-CH-UA-Model, Sec-CH-UA-Platform-Version, Sec-CH-UA-Full-Version-List, Sec-CH-UA-Platform, Sec-CH-UA, UA-Bitness, UA-Arch, UA-Full-Version, UA-Mobile, UA-Model, UA-Platform-Version, UA-Platform, UA",
      "alt-svc": "h3=\":443\"; ma=86400",
      "cf-mitigated": "challenge",
      "critical-ch": "Sec-CH-UA-Bitness, Sec-CH-UA-Arch, Sec-CH-UA-Full-Version, Sec-CH-UA-Mobile, Sec-CH-UA-Model, Sec-CH-UA-Platform-Version, Sec-CH-UA-Full-Version-List, Sec-CH-UA-Platform, Sec-CH-UA, UA-Bitness, UA-Arch, UA-Full-Version, UA-Mobile, UA-Model, UA-Platform-Version, UA-Platform, UA",
      "cross-origin-embedder-policy": "require-corp",
      "cross-origin-opener-policy": "same-origin",
      "cross-origin-resource-policy": "same-origin",
      "origin-agent-cluster": "?1",
      "permissions-policy": "accelerometer=(),browsing-topics=(),camera=(),clipboard-read=(),clipboard-write=(),geolocation=(),gyroscope=(),hid=(),interest-cohort=(),magnetometer=(),microphone=(),payment=(),publickey-credentials-get=(),screen-wake-lock=(),serial=(),sync-xhr=(),usb=()",
      "referrer-policy": "same-origin",
      "server-timing": "chlray;desc=\"9c6dadd51ac655da\", cfL4;desc=\"?proto=TCP&rtt=8574&min_rtt=8409&rtt_var=3271&sent=4&recv=6&lost=0&retrans=0&sent_bytes=2855&recv_bytes=774&delivery_rate=339636&cwnd=250&unsent_bytes=0&cid=2551be23d6e90562&ts=25&x=0\"",
      "x-content-type-options": "nosniff",
      "x-frame-options": "SAMEORIGIN"
    },
    "status": 403,
    "url": "https://www.spiegeldaily.de/category/lebensstil/"
  }
}